futuretone/__init__.py
futuretone/cli.py
futuretone/config.py
futuretone/core.py
futuretone/twitch.py
futuretone-0.0.7.dist-info/METADATA
futuretone-0.0.7.dist-info/WHEEL
futuretone-0.0.7.dist-info/entry_points.txt
futuretone-0.0.7.dist-info/top_level.txt
futuretone-0.0.7.dist-info/RECORD
