Metadata-Version: 2.1
Name: futuretone
Version: 0.0.7
Summary: Integrates into Future Tone on the PS4
Home-page: https://github.com/Jay184/FT-Unofficial/tree/dev/api
Author: Jay
Author-email: 0jaybae0@gmail.com
License: UNKNOWN
Project-URL: Bug Tracker, https://github.com/Jay184/FT-Unofficial/labels/api
Platform: UNKNOWN
Classifier: Programming Language :: Python :: 3
Classifier: Operating System :: OS Independent
Requires-Python: >=3.10
Requires-Dist: click (<8.1.0)
Requires-Dist: pydantic (==1.9.0)
Requires-Dist: twitchio (==2.2.0)
Requires-Dist: typer (==0.4.0)
Requires-Dist: construct (==2.10.68)
Requires-Dist: ps4debug (>=0.1.3)
Provides-Extra: dev
Requires-Dist: pyinstaller ; extra == 'dev'
Requires-Dist: pyinstaller-versionfile ; extra == 'dev'
Requires-Dist: build ; extra == 'dev'
Requires-Dist: twine ; extra == 'dev'
Requires-Dist: pytest ; extra == 'dev'
